topsis_tanisha_102203818/__init__.py
topsis_tanisha_102203818/topsis.py
topsis_Tanisha_102203818-0.1.2.dist-info/LICENSE
topsis_Tanisha_102203818-0.1.2.dist-info/METADATA
topsis_Tanisha_102203818-0.1.2.dist-info/WHEEL
topsis_Tanisha_102203818-0.1.2.dist-info/entry_points.txt
topsis_Tanisha_102203818-0.1.2.dist-info/top_level.txt
topsis_Tanisha_102203818-0.1.2.dist-info/RECORD
