Metadata-Version: 2.2
Name: topsis_Tanisha_102203818
Version: 0.1.2
Summary: A Python package for implementing TOPSIS for multi-criteria decision making
Home-page: https://github.com/tanisha1234-sys/topsis-tanisha-102203818
Author: Tanisha
Author-email: tanishajain286@gmail.com
Classifier: Programming Language :: Python :: 3
Classifier: License :: OSI Approved :: MIT License
Classifier: Operating System :: OS Independent
Requires-Python: >=3.6
License-File: LICENSE
Requires-Dist: numpy>=1.19.5
Requires-Dist: pandas>=1.1.5
Dynamic: author
Dynamic: author-email
Dynamic: classifier
Dynamic: description
Dynamic: description-content-type
Dynamic: home-page
Dynamic: requires-dist
Dynamic: requires-python
Dynamic: summary
